txdpy/__init__.py
txdpy/bk_179.py
txdpy/excel数据或mysql操作.py
txdpy/pyndjs.py
txdpy/其他.py
txdpy/列表操作.py
txdpy/发送邮件.py
txdpy/字符串工具.py
txdpy/字符串类型的判断和提取.py
txdpy/数据去重.py
txdpy/数据库操作.py
txdpy/文本括号及引号不匹配检查.py
txdpy/文本模糊搜索.py
txdpy/文本相似度.py
txdpy/爬虫辅助功能.py
txdpy/百度ai接口使用.py
txdpy/省市区名称的提取或判断.py
txdpy/翻译.py
txdpy/读取pdf.py
txdpy/路径操作.py
txdpy-11.1.1.dist-info/METADATA
txdpy-11.1.1.dist-info/WHEEL
txdpy-11.1.1.dist-info/top_level.txt
txdpy-11.1.1.dist-info/RECORD
