Metadata-Version: 2.4
Name: txdpy
Version: 11.1.1
Author: 唐旭东
Requires-Dist: lxml
Requires-Dist: loguru
Requires-Dist: tqdm
Requires-Dist: colorama
Requires-Dist: openpyxl
Requires-Dist: pymysql
Requires-Dist: xlsxwriter
Requires-Dist: xlrd
Requires-Dist: sshtunnel
Requires-Dist: requests
Requires-Dist: fuzzywuzzy
Requires-Dist: PyMuPDF
Requires-Dist: pdfplumber
Requires-Dist: bs4
Requires-Dist: translate
Requires-Dist: natsort
Requires-Dist: six
Dynamic: author
Dynamic: requires-dist
